medilab/__init__.py
medilab/apps.py
medilab/sitemaps.py
medilab/urls.py
medilab/views.py
medilab/static/medilab/css/style.css
medilab/static/medilab/js/main.js
medilab/static/medilab/scss/_footer.scss
medilab/static/medilab/scss/_general.scss
medilab/static/medilab/scss/_header.scss
medilab/static/medilab/scss/_hero.scss
medilab/static/medilab/scss/_nav.scss
medilab/static/medilab/scss/_sections.scss
medilab/static/medilab/scss/_variables.scss
medilab/static/medilab/scss/style.scss
medilab/static/medilab/vendor/animate.css/animate.compat.css
medilab/static/medilab/vendor/animate.css/animate.css
medilab/static/medilab/vendor/animate.css/animate.min.css
medilab/static/medilab/vendor/bootstrap/css/bootstrap-grid.css
medilab/static/medilab/vendor/bootstrap/css/bootstrap-grid.css.map
medilab/static/medilab/vendor/bootstrap/css/bootstrap-grid.min.css
medilab/static/medilab/vendor/bootstrap/css/bootstrap-grid.min.css.map
medilab/static/medilab/vendor/bootstrap/css/bootstrap-grid.rtl.css
medilab/static/medilab/vendor/bootstrap/css/bootstrap-grid.rtl.css.map
medilab/static/medilab/vendor/bootstrap/css/bootstrap-grid.rtl.min.css
medilab/static/medilab/vendor/bootstrap/css/bootstrap-grid.rtl.min.css.map
medilab/static/medilab/vendor/bootstrap/css/bootstrap-reboot.css
medilab/static/medilab/vendor/bootstrap/css/bootstrap-reboot.css.map
medilab/static/medilab/vendor/bootstrap/css/bootstrap-reboot.min.css
medilab/static/medilab/vendor/bootstrap/css/bootstrap-reboot.min.css.map
medilab/static/medilab/vendor/bootstrap/css/bootstrap-reboot.rtl.css
medilab/static/medilab/vendor/bootstrap/css/bootstrap-reboot.rtl.css.map
medilab/static/medilab/vendor/bootstrap/css/bootstrap-reboot.rtl.min.css
medilab/static/medilab/vendor/bootstrap/css/bootstrap-reboot.rtl.min.css.map
medilab/static/medilab/vendor/bootstrap/css/bootstrap-utilities.css
medilab/static/medilab/vendor/bootstrap/css/bootstrap-utilities.css.map
medilab/static/medilab/vendor/bootstrap/css/bootstrap-utilities.min.css
django_medilab_dental-5.0.7.dist-info/WHEEL
django_medilab_dental-5.0.7.dist-info/METADATA
django_medilab_dental-5.0.7.dist-info/RECORD
