Metadata-Version: 2.3
Name: django_medilab_dental
Version: 5.0.7
Summary: Demiansoft template(medilab)
Requires-Python: >=3.6
Requires-Dist: Django>=4.2.11
Requires-Dist: shared_lib_ds>=1.3.3
